ironic/__init__.py
ironic/version.py
ironic/api/__init__.py
ironic/api/app.py
ironic/api/config.py
ironic/api/functions.py
ironic/api/hooks.py
ironic/api/method.py
ironic/api/wsgi.py
ironic/api/controllers/__init__.py
ironic/api/controllers/base.py
ironic/api/controllers/link.py
ironic/api/controllers/root.py
ironic/api/controllers/version.py
ironic/api/controllers/v1/__init__.py
ironic/api/controllers/v1/allocation.py
ironic/api/controllers/v1/bios.py
ironic/api/controllers/v1/chassis.py
ironic/api/controllers/v1/collection.py
ironic/api/controllers/v1/conductor.py
ironic/api/controllers/v1/deploy_template.py
ironic/api/controllers/v1/driver.py
ironic/api/controllers/v1/event.py
ironic/api/controllers/v1/firmware.py
ironic/api/controllers/v1/inspection_rule.py
ironic/api/controllers/v1/network-data-schema.json
ironic/api/controllers/v1/node.py
ironic/api/controllers/v1/notification_utils.py
ironic/api/controllers/v1/port.py
ironic/api/controllers/v1/portgroup.py
ironic/api/controllers/v1/ramdisk.py
ironic/api/controllers/v1/runbook.py
ironic/api/controllers/v1/shard.py
ironic/api/controllers/v1/utils.py
ironic/api/controllers/v1/versions.py
ironic/api/controllers/v1/volume.py
ironic/api/controllers/v1/volume_connector.py
ironic/api/controllers/v1/volume_target.py
ironic/api/middleware/__init__.py
ironic/api/middleware/auth_public_routes.py
ironic/api/middleware/json_ext.py
ironic/api/middleware/parsable_error.py
ironic/api/middleware/request_log.py
ironic/api/schemas/common/__init__.py
ironic/api/schemas/common/request_types.py
ironic/api/schemas/common/response_types.py
ironic/api/schemas/v1/allocation.py
ironic/api/schemas/v1/bios.py
ironic/api/schemas/v1/firmware.py
ironic/api/schemas/v1/inspection_rule.py
ironic/api/schemas/v1/shard.py
ironic/api/validation/__init__.py
ironic/api/validation/validators.py
ironic/command/__init__.py
ironic/command/api.py
ironic/command/conductor.py
ironic/command/dbsync.py
ironic/command/novncproxy.py
ironic-33.0.0.dist-info/AUTHORS
ironic-33.0.0.dist-info/LICENSE
ironic-33.0.0.dist-info/METADATA
ironic-33.0.0.dist-info/WHEEL
ironic-33.0.0.dist-info/entry_points.txt
ironic-33.0.0.dist-info/pbr.json
ironic-33.0.0.dist-info/top_level.txt
ironic-33.0.0.dist-info/RECORD
