Metadata-Version: 2.1
Name: ironic
Version: 33.0.0
Summary: OpenStack Bare Metal Provisioning
Author-email: OpenStack <openstack-discuss@lists.openstack.org>
License: Apache-2.0
Project-URL: Homepage, https://docs.openstack.org/ironic
Project-URL: Repository, https://opendev.org/openstack/ironic
Project-URL: Bugs, https://bugs.launchpad.net/ironic
Classifier: Development Status :: 5 - Production/Stable
Classifier: Environment :: OpenStack
Classifier: Intended Audience :: Information Technology
Classifier: Intended Audience :: System Administrators
Classifier: License :: OSI Approved :: Apache Software License
Classifier: Operating System :: POSIX :: Linux
Classifier: Programming Language :: Python
Classifier: Programming Language :: Python :: 3
Classifier: Programming Language :: Python :: 3.10
Classifier: Programming Language :: Python :: 3.11
Classifier: Programming Language :: Python :: 3.12
Classifier: Programming Language :: Python :: 3.13
Requires-Python: >=3.10
License-File: LICENSE
License-File: AUTHORS
Requires-Dist: pbr >=6.0.0
Requires-Dist: SQLAlchemy >=1.4.0
Requires-Dist: alembic >=1.4.2
Requires-Dist: automaton >=1.9.0
Requires-Dist: WebOb >=1.7.1
Requires-Dist: keystoneauth1 >=4.2.0
Requires-Dist: stevedore >=1.29.0
Requires-Dist: oslo.concurrency >=4.2.0
Requires-Dist: oslo.config >=6.8.0
Requires-Dist: oslo.context >=2.22.0
Requires-Dist: oslo.db >=9.1.0
Requires-Dist: oslo.log >=4.3.0
Requires-Dist: oslo.middleware >=3.31.0
Requires-Dist: oslo.policy >=4.5.0
Requires-Dist: oslo.serialization >=2.25.0
Requires-Dist: oslo.service >=4.2.1
Requires-Dist: oslo.upgradecheck >=1.3.0
Requires-Dist: oslo.utils >=8.0.0
Requires-Dist: osprofiler >=1.5.0
Requires-Dist: os-traits >=0.4.0
Requires-Dist: pecan >=1.0.0
Requires-Dist: pycdlib >=1.11.0
Requires-Dist: requests >=2.18.0
Requires-Dist: rfc3986 >=1.2.0
Requires-Dist: jsonpatch >=1.16
Requires-Dist: Jinja2 >=3.1.6
Requires-Dist: keystonemiddleware >=9.5.0
Requires-Dist: oslo.messaging >=14.1.0
Requires-Dist: tenacity >=6.3.1
Requires-Dist: oslo.versionedobjects >=1.31.2
Requires-Dist: jsonschema >=4.0.0
Requires-Dist: psutil >=3.2.2
Requires-Dist: futurist >=3.2.0
Requires-Dist: tooz >=2.7.0
Requires-Dist: openstacksdk >=0.99.0
Requires-Dist: sushy >=5.7.0
Requires-Dist: construct >=2.9.39
Requires-Dist: netaddr >=0.9.0
Requires-Dist: microversion-parse >=1.0.1
Requires-Dist: zeroconf >=0.24.0
Requires-Dist: os-service-types >=1.7.0
Requires-Dist: bcrypt >=3.1.3
Requires-Dist: websockify >=0.9.0
Requires-Dist: PyYAML >=6.0.2
Requires-Dist: cheroot >=10.0.1
Requires-Dist: cotyledon >=2.0.0
Requires-Dist: lark >=1.2.2
Provides-Extra: devstack
Requires-Dist: virtualbmc >=1.4.0 ; extra == 'devstack'
Provides-Extra: guru_meditation_reports
Requires-Dist: oslo.reports >=1.18.0 ; extra == 'guru_meditation_reports'
Provides-Extra: i18n
Requires-Dist: oslo.i18n >=3.20.0 ; extra == 'i18n'
